pytomfig/__init__.py
pytomfig/main.py
pytomfig_Sluke950-0.0.1.dist-info/METADATA
pytomfig_Sluke950-0.0.1.dist-info/WHEEL
pytomfig_Sluke950-0.0.1.dist-info/top_level.txt
pytomfig_Sluke950-0.0.1.dist-info/RECORD
