Metadata-Version: 2.1
Name: pytomfig_Sluke950
Version: 0.0.1
Summary: TOML configuration file manager.
Author-email: Luke Shuttleworth <Sluke950@gmail.com>
Project-URL: Homepage, https://github.com/Sluke950/pytomfig
Project-URL: Issues, https://github.com/Sluke950/pytomfig/issues
Classifier: Programming Language :: Python :: 3
Classifier: License :: OSI Approved :: MIT License
Classifier: Operating System :: OS Independent
Requires-Python: >=3.8
